reduce_smell_detector/__init__.py
reduce_smell_detector/detector.py
reduce_smell_detector/main.py
reduce_smell_detector/parser.py
reduce_smell_detector/results.py
reduce_smell_detector/smell_detection.py
reduce_smell_detector-0.3.dist-info/METADATA
reduce_smell_detector-0.3.dist-info/WHEEL
reduce_smell_detector-0.3.dist-info/entry_points.txt
reduce_smell_detector-0.3.dist-info/top_level.txt
reduce_smell_detector-0.3.dist-info/RECORD
